boto3_wrappers/__init__.py
boto3_wrappers/client.py
boto3_wrappers/cloudformation.py
boto3_wrappers-0.2.1.dist-info/LICENSE
boto3_wrappers-0.2.1.dist-info/METADATA
boto3_wrappers-0.2.1.dist-info/WHEEL
boto3_wrappers-0.2.1.dist-info/top_level.txt
boto3_wrappers-0.2.1.dist-info/RECORD
